geoarrow/pyarrow/__init__.py
geoarrow/pyarrow/_array.py
geoarrow/pyarrow/_compute.py
geoarrow/pyarrow/_kernel.py
geoarrow/pyarrow/_scalar.py
geoarrow/pyarrow/_type.py
geoarrow/pyarrow/dataset.py
geoarrow/pyarrow/io.py
geoarrow_pyarrow-0.1.1.dist-info/METADATA
geoarrow_pyarrow-0.1.1.dist-info/WHEEL
geoarrow_pyarrow-0.1.1.dist-info/top_level.txt
geoarrow_pyarrow-0.1.1.dist-info/RECORD
